{
  "source": "dev",
  "key": "0a532a20-999f-4a60-805c-376a70c415f6",
  "ownerGuid": "e9a4ec64daebd274090fec604bd012e7",
  "languages": [
    {
      "locale": "Sound",
      "text": "",
      "modification_date": "2025-10-28T11:07:08.9483563Z"
    },
    {
      "locale": "dev",
      "text": "{uip|dmg %|203ee372474748a19f5a96a538d23c1d}% урона и {uip|stats|203ee372474748a19f5a96a538d23c1d} всех статов на 2 хода. Стакается 6 раз.",
      "modification_date": "2026-02-26T16:03:18.7791041Z",
      "traits": [
        {
          "trait": "CheckMe",
          "trait_date": "2026-02-26T16:03:18.7791041Z",
          "locale_text": "{uip|dmg %|203ee372474748a19f5a96a538d23c1d}% урона и {uip|stats|203ee372474748a19f5a96a538d23c1d} всех статов на 2 хода. Стакается 6 раз.",
          "speaker": "",
          "speaker_gender": ""
        }
      ]
    },
    {
      "locale": "enGB",
      "text": "The damage dealt by this character is increased by +{uip|dmg %|203ee372474748a19f5a96a538d23c1d}%, and all their {g|Encyclopedia:Characteristic}characteristics{/g} are increased by +{uip|stats|203ee372474748a19f5a96a538d23c1d} for 2 {g|Encyclopedia:Round}rounds{/g}. Stacks up to 6 times.",
      "modification_date": "2026-04-10T11:12:46.8323697Z",
      "translated_from": "dev",
      "translation_date": "2026-04-08T17:22:13.6198797Z",
      "original_text": "{uip|dmg %|203ee372474748a19f5a96a538d23c1d}% урона и {uip|stats|203ee372474748a19f5a96a538d23c1d} всех статов на 2 хода. Стакается 6 раз.",
      "traits": [
        {
          "trait": "GD_ok",
          "trait_date": "2026-04-08T17:22:10.9072393Z",
          "locale_text": "The damage dealt by this character is increased by +{uip|dmg %|203ee372474748a19f5a96a538d23c1d}%, and all their characteristics are increased by +{uip|stats|203ee372474748a19f5a96a538d23c1d} for 2 rounds. Stacks up to 6 times."
        },
        {
          "trait": "Edited",
          "trait_date": "2026-04-22T05:40:33.3970747Z",
          "locale_text": "The damage dealt by this character is increased by +{uip|dmg %|203ee372474748a19f5a96a538d23c1d}%, and all their {g|Encyclopedia:Characteristic}characteristics{/g} are increased by +{uip|stats|203ee372474748a19f5a96a538d23c1d} for 2 {g|Encyclopedia:Round}rounds{/g}. Stacks up to 6 times."
        },
        {
          "trait": "JL_ed",
          "trait_date": "2026-04-09T13:14:34.7959045Z",
          "locale_text": "The damage dealt by this character is increased by +{uip|dmg %|203ee372474748a19f5a96a538d23c1d}%, and all their characteristics are increased by +{uip|stats|203ee372474748a19f5a96a538d23c1d} for 2 rounds. Stacks up to 6 times."
        },
        {
          "trait": "Sent_for_Translation",
          "trait_date": "2026-04-21T08:42:40.8482663Z",
          "locale_text": "The damage dealt by this character is increased by +{uip|dmg %|203ee372474748a19f5a96a538d23c1d}%, and all their {g|Encyclopedia:Characteristic}characteristics{/g} are increased by +{uip|stats|203ee372474748a19f5a96a538d23c1d} for 2 {g|Encyclopedia:Round}rounds{/g}. Stacks up to 6 times."
        }
      ]
    },
    {
      "locale": "ruRU",
      "text": "Это персонаж наносит +{uip|dmg %|203ee372474748a19f5a96a538d23c1d}% больше урона и все его {g|Encyclopedia:Characteristic}характеристики{/g} увеличены на +{uip|stats|203ee372474748a19f5a96a538d23c1d} на 2 {g|Encyclopedia:Round}раунда{/g}. Суммируется до 6 раз.",
      "modification_date": "2026-06-06T14:21:16.1343629Z",
      "translated_from": "enGB",
      "translation_date": "2026-06-06T14:21:16.1343631Z",
      "original_text": "The damage dealt by this character is increased by +{uip|dmg %|203ee372474748a19f5a96a538d23c1d}%, and all their {g|Encyclopedia:Characteristic}characteristics{/g} are increased by +{uip|stats|203ee372474748a19f5a96a538d23c1d} for 2 {g|Encyclopedia:Round}rounds{/g}. Stacks up to 6 times.",
      "traits": [
        {
          "trait": "Translated",
          "trait_date": "2026-06-06T14:21:16.1343646Z",
          "locale_text": "Это персонаж наносит +{uip|dmg %|203ee372474748a19f5a96a538d23c1d}% больше урона и все его {g|Encyclopedia:Characteristic}характеристики{/g} увеличены на +{uip|stats|203ee372474748a19f5a96a538d23c1d} на 2 {g|Encyclopedia:Round}раунда{/g}. Суммируется до 6 раз."
        },
        {
          "trait": "VO_tr",
          "trait_date": "2026-06-06T14:21:16.1343649Z",
          "locale_text": "Это персонаж наносит +{uip|dmg %|203ee372474748a19f5a96a538d23c1d}% больше урона и все его {g|Encyclopedia:Characteristic}характеристики{/g} увеличены на +{uip|stats|203ee372474748a19f5a96a538d23c1d} на 2 {g|Encyclopedia:Round}раунда{/g}. Суммируется до 6 раз."
        }
      ]
    },
    {
      "locale": "frFR",
      "text": "Les dégâts infligés par ce personnage augmentent de +{uip|dmg %|203ee372474748a19f5a96a538d23c1d} % et toutes ses {g|Encyclopedia:Characteristic}caractéristiques{/g} de +{uip|stats|203ee372474748a19f5a96a538d23c1d} pendant 2 {g|Encyclopedia:Round}rounds{/g}. Cumulable jusqu'à 6 fois.",
      "modification_date": "2026-04-17T10:13:51.2331064Z",
      "translated_from": "enGB",
      "translation_date": "2026-04-17T10:13:51.2331066Z",
      "original_text": "The damage dealt by this character is increased by +{uip|dmg %|203ee372474748a19f5a96a538d23c1d}%, and all their {g|Encyclopedia:Characteristic}characteristics{/g} are increased by +{uip|stats|203ee372474748a19f5a96a538d23c1d} for 2 {g|Encyclopedia:Round}rounds{/g}. Stacks up to 6 times.",
      "traits": [
        {
          "trait": "Translated",
          "trait_date": "2026-04-17T10:13:51.2331071Z",
          "locale_text": "Les dégâts infligés par ce personnage augmentent de +{uip|dmg %|203ee372474748a19f5a96a538d23c1d} % et toutes ses {g|Encyclopedia:Characteristic}caractéristiques{/g} de +{uip|stats|203ee372474748a19f5a96a538d23c1d} pendant 2 {g|Encyclopedia:Round}rounds{/g}. Cumulable jusqu'à 6 fois."
        }
      ]
    },
    {
      "locale": "trTR",
      "text": "Bu karakterin verdiği hasar +%{uip|dmg %|203ee372474748a19f5a96a538d23c1d}, tüm {g|Encyclopedia:Characteristic}nitelikleri{/g} ise +{uip|stats|203ee372474748a19f5a96a538d23c1d} artar. Etkisi 2 {g|Encyclopedia:Round}raunt{/g} sürer. 6 kez üst üste birikebilir.",
      "modification_date": "2026-04-20T07:31:18.3472326Z",
      "translated_from": "enGB",
      "translation_date": "2026-04-20T07:31:18.3472328Z",
      "original_text": "The damage dealt by this character is increased by +{uip|dmg %|203ee372474748a19f5a96a538d23c1d}%, and all their {g|Encyclopedia:Characteristic}characteristics{/g} are increased by +{uip|stats|203ee372474748a19f5a96a538d23c1d} for 2 {g|Encyclopedia:Round}rounds{/g}. Stacks up to 6 times.",
      "traits": [
        {
          "trait": "Translated",
          "trait_date": "2026-04-20T07:31:18.3472333Z",
          "locale_text": "Bu karakterin verdiği hasar +%{uip|dmg %|203ee372474748a19f5a96a538d23c1d}, tüm {g|Encyclopedia:Characteristic}nitelikleri{/g} ise +{uip|stats|203ee372474748a19f5a96a538d23c1d} artar. Etkisi 2 {g|Encyclopedia:Round}raunt{/g} sürer. 6 kez üst üste birikebilir."
        }
      ]
    },
    {
      "locale": "zhCN",
      "text": "该角色造成伤害提高{uip|dmg %|203ee372474748a19f5a96a538d23c1d}%，所有{g|Encyclopedia:Characteristic}属性{/g}提高{uip|stats|203ee372474748a19f5a96a538d23c1d}点，持续2{g|Encyclopedia:Round}轮{/g}。最多叠加6次。",
      "modification_date": "2026-04-20T07:33:44.3749874Z",
      "translated_from": "enGB",
      "translation_date": "2026-04-20T07:33:44.3749875Z",
      "original_text": "The damage dealt by this character is increased by +{uip|dmg %|203ee372474748a19f5a96a538d23c1d}%, and all their {g|Encyclopedia:Characteristic}characteristics{/g} are increased by +{uip|stats|203ee372474748a19f5a96a538d23c1d} for 2 {g|Encyclopedia:Round}rounds{/g}. Stacks up to 6 times.",
      "traits": [
        {
          "trait": "Translated",
          "trait_date": "2026-04-20T07:33:44.3749881Z",
          "locale_text": "该角色造成伤害提高{uip|dmg %|203ee372474748a19f5a96a538d23c1d}%，所有{g|Encyclopedia:Characteristic}属性{/g}提高{uip|stats|203ee372474748a19f5a96a538d23c1d}点，持续2{g|Encyclopedia:Round}轮{/g}。最多叠加6次。"
        }
      ]
    },
    {
      "locale": "esES",
      "text": "El daño que inflige este personaje aumenta un +{uip|dmg %|203ee372474748a19f5a96a538d23c1d} %, y todas sus {g|Encyclopedia:Characteristic}características{/g} aumentan en +{uip|stats|203ee372474748a19f5a96a538d23c1d} durante 2 {g|Encyclopedia:Round}asaltos{/g}. Este efecto se acumula un máximo de 6 veces.",
      "modification_date": "2026-04-20T07:48:10.8408900Z",
      "translated_from": "enGB",
      "translation_date": "2026-04-20T07:48:10.8408901Z",
      "original_text": "The damage dealt by this character is increased by +{uip|dmg %|203ee372474748a19f5a96a538d23c1d}%, and all their {g|Encyclopedia:Characteristic}characteristics{/g} are increased by +{uip|stats|203ee372474748a19f5a96a538d23c1d} for 2 {g|Encyclopedia:Round}rounds{/g}. Stacks up to 6 times.",
      "traits": [
        {
          "trait": "Translated",
          "trait_date": "2026-04-20T07:48:10.8408907Z",
          "locale_text": "El daño que inflige este personaje aumenta un +{uip|dmg %|203ee372474748a19f5a96a538d23c1d} %, y todas sus {g|Encyclopedia:Characteristic}características{/g} aumentan en +{uip|stats|203ee372474748a19f5a96a538d23c1d} durante 2 {g|Encyclopedia:Round}asaltos{/g}. Este efecto se acumula un máximo de 6 veces."
        }
      ]
    },
    {
      "locale": "deDE",
      "text": "Der durch diesen Charakter verursachte Schaden erhöht sich um +{uip|dmg %|203ee372474748a19f5a96a538d23c1d} %, und seine {g|Encyclopedia:Characteristic}Eigenschaften{/g} erhöhen sich 2 {g|Encyclopedia:Round}Runden{/g} lang um +{uip|stats|203ee372474748a19f5a96a538d23c1d}. Bis zu 6-mal stapelbar.",
      "modification_date": "2026-04-24T10:25:07.7616862Z",
      "translated_from": "enGB",
      "translation_date": "2026-04-24T10:25:07.7616864Z",
      "original_text": "The damage dealt by this character is increased by +{uip|dmg %|203ee372474748a19f5a96a538d23c1d}%, and all their {g|Encyclopedia:Characteristic}characteristics{/g} are increased by +{uip|stats|203ee372474748a19f5a96a538d23c1d} for 2 {g|Encyclopedia:Round}rounds{/g}. Stacks up to 6 times.",
      "traits": [
        {
          "trait": "Translated",
          "trait_date": "2026-04-24T10:25:07.7616881Z",
          "locale_text": "Der durch diesen Charakter verursachte Schaden erhöht sich um +{uip|dmg %|203ee372474748a19f5a96a538d23c1d} %, und seine {g|Encyclopedia:Characteristic}Eigenschaften{/g} erhöhen sich 2 {g|Encyclopedia:Round}Runden{/g} lang um +{uip|stats|203ee372474748a19f5a96a538d23c1d}. Bis zu 6-mal stapelbar."
        }
      ]
    },
    {
      "locale": "jaJP",
      "text": "このキャラクターが与えるダメージが+{uip|dmg %|203ee372474748a19f5a96a538d23c1d}%増加し、全{g|Encyclopedia:Characteristic}能力値{/g}が2{g|Encyclopedia:Round}ラウンド{/g}の間+{uip|stats|203ee372474748a19f5a96a538d23c1d}増加する。最大6回までスタックする。",
      "modification_date": "2026-06-05T10:18:40.0239196Z",
      "translated_from": "enGB",
      "translation_date": "2026-06-05T14:15:14.8542373Z",
      "original_text": "The damage dealt by this character is increased by +{uip|dmg %|203ee372474748a19f5a96a538d23c1d}%, and all their {g|Encyclopedia:Characteristic}characteristics{/g} are increased by +{uip|stats|203ee372474748a19f5a96a538d23c1d} for 2 {g|Encyclopedia:Round}rounds{/g}. Stacks up to 6 times.",
      "traits": [
        {
          "trait": "AIGenerated",
          "trait_date": "2026-06-05T14:15:14.8542389Z",
          "locale_text": "このキャラクターが与えるダメージが+{uip|dmg %|203ee372474748a19f5a96a538d23c1d}%増加し、全{g|Encyclopedia:Characteristic}能力値{/g}が2{g|Encyclopedia:Round}ラウンド{/g}の間+{uip|stats|203ee372474748a19f5a96a538d23c1d}増加する。最大6回までスタックする。"
        }
      ]
    }
  ],
  "string_traits": [
    {
      "trait": "второй_батч_механ",
      "trait_date": "2026-04-10T11:33:53.3946557Z",
      "locale_text": ""
    },
    {
      "trait": "Sent_otherloc",
      "trait_date": "2026-04-13T09:05:52.8927358Z",
      "locale_text": ""
    },
    {
      "trait": "в_работе",
      "trait_date": "2026-04-13T09:05:52.8927360Z",
      "locale_text": ""
    },
    {
      "trait": "nikolai",
      "trait_date": "2026-04-14T08:56:08.5361084Z",
      "locale_text": ""
    },
    {
      "trait": "DLC3",
      "trait_date": "2026-04-16T14:28:36.6712575Z",
      "locale_text": ""
    },
    {
      "trait": "DLC3_mech",
      "trait_date": "2026-04-16T14:28:36.6712577Z",
      "locale_text": ""
    },
    {
      "trait": "Отдала_Владе",
      "trait_date": "2026-05-28T19:23:27.5942524Z",
      "locale_text": ""
    }
  ]
}