{
  "source": "ruRU",
  "key": "346cb5b2-d8c8-429c-94d5-8f4dbef3712c",
  "ownerGuid": "b1d6707938274f92a9900c38a52c6f39",
  "languages": [
    {
      "locale": "ruRU",
      "text": "\"Я же приказал{mf||а} прекратить побои!\"",
      "modification_date": "2024-07-16T16:58:32.4954472Z",
      "traits": []
    },
    {
      "locale": "enGB",
      "text": "\"I ordered that the beatings be stopped!\"",
      "modification_date": "2024-07-31T16:58:25.9538088Z",
      "translated_from": "ruRU",
      "translation_date": "2024-08-02T13:32:42.4229454Z",
      "original_text": "\"Я же приказал{mf||а} прекратить побои!\"",
      "traits": [
        {
          "trait": "Translated",
          "trait_date": "2024-07-31T16:58:25.9538116Z",
          "locale_text": "\"I ordered that the beatings be stopped!\""
        },
        {
          "trait": "Edited",
          "trait_date": "2024-07-31T16:58:25.9538121Z",
          "locale_text": "\"I ordered that the beatings be stopped!\""
        },
        {
          "trait": "AD_tr_ed",
          "trait_date": "2024-07-31T16:58:25.9538123Z",
          "locale_text": "\"I ordered that the beatings be stopped!\""
        },
        {
          "trait": "TK_rv",
          "trait_date": "2024-08-02T13:32:42.4229476Z",
          "locale_text": "\"I ordered that the beatings be stopped!\""
        },
        {
          "trait": "Turkish",
          "trait_date": "2024-09-16T12:12:18.7142799Z",
          "locale_text": "\"I ordered that the beatings be stopped!\""
        }
      ]
    },
    {
      "locale": "zhCN",
      "text": "“我明明已经下过命令，禁止殴打船员！”",
      "modification_date": "2024-08-30T15:33:10.1343533Z",
      "translated_from": "enGB",
      "translation_date": "2024-08-30T15:33:10.1343564Z",
      "original_text": "\"I ordered that the beatings be stopped!\"",
      "traits": [
        {
          "trait": "Translated",
          "trait_date": "2024-08-30T15:33:10.1343590Z",
          "locale_text": "“我明明已经下过命令，禁止殴打船员！”"
        }
      ]
    },
    {
      "locale": "esES",
      "text": "«¡Ordeno que se ponga fin a las palizas!».",
      "modification_date": "2024-08-30T15:34:07.7160009Z",
      "translated_from": "enGB",
      "translation_date": "2024-08-30T15:34:07.7160012Z",
      "original_text": "\"I ordered that the beatings be stopped!\"",
      "traits": [
        {
          "trait": "Translated",
          "trait_date": "2024-08-30T15:34:07.7160018Z",
          "locale_text": "«¡Ordeno que se ponga fin a las palizas!»."
        }
      ]
    },
    {
      "locale": "jaJP",
      "text": "「殴るのは禁止と言っただろう！」",
      "modification_date": "2024-08-30T15:34:48.0826219Z",
      "translated_from": "enGB",
      "translation_date": "2024-08-30T15:34:48.0826222Z",
      "original_text": "\"I ordered that the beatings be stopped!\"",
      "traits": [
        {
          "trait": "Translated",
          "trait_date": "2024-08-30T15:34:48.0826234Z",
          "locale_text": "「殴るのは禁止と言っただろう！」"
        }
      ]
    },
    {
      "locale": "deDE",
      "text": "\"Ich habe angeordnet, die Prügel einzustellen.\"",
      "modification_date": "2024-09-10T10:39:03.0135247Z",
      "translated_from": "enGB",
      "translation_date": "2024-09-10T10:39:03.0135250Z",
      "original_text": "\"I ordered that the beatings be stopped!\"",
      "traits": [
        {
          "trait": "Translated",
          "trait_date": "2024-09-10T10:39:03.0135276Z",
          "locale_text": "\"Ich habe angeordnet, die Prügel einzustellen.\""
        }
      ]
    },
    {
      "locale": "frFR",
      "text": "« J'ai ordonné que cessent les passages à tabac ! »",
      "modification_date": "2024-09-11T09:53:37.2881988Z",
      "translated_from": "enGB",
      "translation_date": "2024-09-11T09:53:37.2881991Z",
      "original_text": "\"I ordered that the beatings be stopped!\"",
      "traits": [
        {
          "trait": "Translated",
          "trait_date": "2024-09-11T09:53:37.2882008Z",
          "locale_text": "« J'ai ordonné que cessent les passages à tabac ! »"
        }
      ]
    },
    {
      "locale": "trTR",
      "text": "\"Dayağın sona ermesini emretmiştim!\"",
      "modification_date": "2025-01-21T10:49:49.8415374Z",
      "translated_from": "enGB",
      "translation_date": "2025-01-21T10:49:49.8415376Z",
      "original_text": "\"I ordered that the beatings be stopped!\"",
      "traits": [
        {
          "trait": "Translated",
          "trait_date": "2026-06-10T16:43:32.4350005Z",
          "locale_text": "\"Dayağın sona ermesini emretmiştim!\""
        }
      ]
    },
    {
      "locale": "Sound",
      "text": "",
      "modification_date": "2025-12-03T11:07:08.8410401Z"
    }
  ],
  "string_traits": [
    {
      "trait": "DLC1",
      "trait_date": "2024-07-30T07:00:09.4349260Z",
      "locale_text": ""
    }
  ]
}