{
  "source": "ruRU",
  "key": "4e1d87be-5340-44a3-b651-edab8f6aaed2",
  "ownerGuid": "2be9591cf864a504fa98683cd539c614",
  "languages": [
    {
      "locale": "ruRU",
      "text": "\"Ммм... Изысканный аромат... Невозможно остановиться\".",
      "modification_date": "2024-06-03T07:54:31.8265256Z",
      "traits": [
        {
          "trait": "CheckMe",
          "trait_date": "2024-06-01T14:30:23.5297080Z",
          "locale_text": "\"Ммм... О да, этот изысканный аромат... Невозможно остановиться\"."
        }
      ]
    },
    {
      "locale": "dev",
      "text": "",
      "modification_date": "2024-06-01T14:25:18.1481247Z",
      "traits": []
    },
    {
      "locale": "enGB",
      "text": "\"Mmm... An exquisite flavour... I simply cannot stop.\"",
      "modification_date": "2024-06-24T17:46:24.5264402Z",
      "translated_from": "ruRU",
      "translation_date": "2024-07-01T14:41:35.9164411Z",
      "original_text": "\"Ммм... Изысканный аромат... Невозможно остановиться\".",
      "traits": [
        {
          "trait": "Translated",
          "trait_date": "2024-06-11T12:12:56.7195785Z",
          "locale_text": "\"Hmmm... An exquisite flavour... Impossible to stop.\""
        },
        {
          "trait": "NE_tr",
          "trait_date": "2024-06-11T12:12:56.7195788Z",
          "locale_text": "\"Hmmm... An exquisite flavour... Impossible to stop.\""
        },
        {
          "trait": "Edited",
          "trait_date": "2024-06-24T17:46:24.5264418Z",
          "locale_text": "\"Mmm... An exquisite flavour... I simply cannot stop.\""
        },
        {
          "trait": "MA_ed",
          "trait_date": "2024-06-24T17:46:24.5264421Z",
          "locale_text": "\"Mmm... An exquisite flavour... I simply cannot stop.\""
        },
        {
          "trait": "TK_rv",
          "trait_date": "2024-07-01T14:41:35.9164431Z",
          "locale_text": "\"Mmm... An exquisite flavour... I simply cannot stop.\""
        },
        {
          "trait": "Turkish",
          "trait_date": "2024-09-16T12:12:00.5787700Z",
          "locale_text": "\"Mmm... An exquisite flavour... I simply cannot stop.\""
        }
      ]
    },
    {
      "locale": "frFR",
      "text": "« Mmm... Quel goût exquis... Je suis incapable de m'arrêter. »",
      "modification_date": "2024-09-19T12:29:16.1691066Z",
      "translated_from": "enGB",
      "translation_date": "2024-09-19T12:29:16.1691070Z",
      "original_text": "\"Mmm... An exquisite flavour... I simply cannot stop.\"",
      "traits": [
        {
          "trait": "Translated",
          "trait_date": "2024-09-19T12:29:16.1691085Z",
          "locale_text": "« Mmm... Quel goût exquis... Je suis incapable de m'arrêter. »"
        }
      ]
    },
    {
      "locale": "esES",
      "text": "«Hum... Un sabor exquisito... No puedo parar ahora».",
      "modification_date": "2024-09-20T14:27:35.0859529Z",
      "translated_from": "enGB",
      "translation_date": "2024-09-20T14:27:35.0859530Z",
      "original_text": "\"Mmm... An exquisite flavour... I simply cannot stop.\"",
      "traits": [
        {
          "trait": "Translated",
          "trait_date": "2024-09-20T14:27:35.0859535Z",
          "locale_text": "«Hum... Un sabor exquisito... No puedo parar ahora»."
        }
      ]
    },
    {
      "locale": "jaJP",
      "text": "「うーん…絶妙な風味… やめられないなぁ」",
      "modification_date": "2024-09-20T14:31:00.0794898Z",
      "translated_from": "enGB",
      "translation_date": "2024-09-20T14:31:00.0794900Z",
      "original_text": "\"Mmm... An exquisite flavour... I simply cannot stop.\"",
      "traits": [
        {
          "trait": "Translated",
          "trait_date": "2024-09-20T14:31:00.0794904Z",
          "locale_text": "「うーん…絶妙な風味… やめられないなぁ」"
        }
      ]
    },
    {
      "locale": "zhCN",
      "text": "“嗯……何等精致的味道……真是让人停不下来。”",
      "modification_date": "2024-09-20T14:34:53.9581099Z",
      "translated_from": "enGB",
      "translation_date": "2024-09-20T14:34:53.9581101Z",
      "original_text": "\"Mmm... An exquisite flavour... I simply cannot stop.\"",
      "traits": [
        {
          "trait": "Translated",
          "trait_date": "2024-09-20T14:34:53.9581107Z",
          "locale_text": "“嗯……何等精致的味道……真是让人停不下来。”"
        }
      ]
    },
    {
      "locale": "deDE",
      "text": "\"Hmm ... Köstlich ... Ich kann gar nicht aufhören.\"",
      "modification_date": "2024-09-20T15:15:38.4895654Z",
      "translated_from": "enGB",
      "translation_date": "2024-09-20T15:15:38.4895656Z",
      "original_text": "\"Mmm... An exquisite flavour... I simply cannot stop.\"",
      "traits": [
        {
          "trait": "Translated",
          "trait_date": "2024-09-20T15:15:38.4895661Z",
          "locale_text": "\"Hmm ... Köstlich ... Ich kann gar nicht aufhören.\""
        }
      ]
    },
    {
      "locale": "trTR",
      "text": "\"Hımm... Enfes bir lezzet... Bir türlü bırakamıyorum.\"",
      "modification_date": "2025-01-21T10:49:22.5212579Z",
      "translated_from": "enGB",
      "translation_date": "2025-01-21T10:49:22.5212581Z",
      "original_text": "\"Mmm... An exquisite flavour... I simply cannot stop.\"",
      "traits": [
        {
          "trait": "Translated",
          "trait_date": "2026-06-10T16:43:08.8406561Z",
          "locale_text": "\"Hımm... Enfes bir lezzet... Bir türlü bırakamıyorum.\""
        }
      ]
    },
    {
      "locale": "Sound",
      "text": "",
      "modification_date": "2025-12-03T11:00:34.6185113Z"
    }
  ],
  "string_traits": [
    {
      "trait": "DLC1",
      "trait_date": "2024-06-03T10:00:25.3695672Z",
      "locale_text": ""
    },
    {
      "trait": "тест_1",
      "trait_date": "2025-08-21T08:50:52.6952485Z",
      "locale_text": ""
    }
  ]
}