{
  "source": "dev",
  "key": "62017ea3-3d84-483d-8b71-575842f8e775",
  "ownerGuid": "792ae4d58f400154cbffe7d0e9b6ff95",
  "languages": [
    {
      "locale": "dev",
      "text": "Mass Shove",
      "modification_date": "2025-05-12T13:24:22.3210612Z",
      "traits": [
        {
          "trait": "CheckMe",
          "trait_date": "2025-05-12T13:24:22.3210612Z",
          "locale_text": "Mass Shove",
          "speaker": "",
          "speaker_gender": ""
        }
      ]
    },
    {
      "locale": "enGB",
      "text": "Shoving Strike",
      "modification_date": "2025-05-14T21:28:35.1950855Z",
      "translated_from": "ruRU",
      "translation_date": "2025-05-27T11:07:08.9115910Z",
      "original_text": "Отбрасывающий удар",
      "traits": [
        {
          "trait": "GD_ok",
          "trait_date": "2025-05-14T21:29:16.3344336Z",
          "locale_text": "Shoving Strike"
        },
        {
          "trait": "Edited",
          "trait_date": "2025-05-27T11:07:08.9115916Z",
          "locale_text": "Shoving Strike"
        },
        {
          "trait": "JL_ed",
          "trait_date": "2025-05-27T11:07:08.9115918Z",
          "locale_text": "Shoving Strike"
        }
      ]
    },
    {
      "locale": "ruRU",
      "text": "Отбрасывающий удар",
      "modification_date": "2025-05-14T21:28:42.8699608Z",
      "translated_from": "enGB",
      "translation_date": "2025-05-14T21:29:00.6193302Z",
      "original_text": "Shoving Strike",
      "traits": [
        {
          "trait": "Translated",
          "trait_date": "2025-05-14T21:29:23.3732639Z",
          "locale_text": "Отбрасывающий удар"
        }
      ]
    },
    {
      "locale": "deDE",
      "text": "Drängender Hieb",
      "modification_date": "2025-06-18T05:13:45.6760783Z",
      "translated_from": "enGB",
      "translation_date": "2025-06-18T05:13:45.6760785Z",
      "original_text": "Shoving Strike",
      "traits": [
        {
          "trait": "Translated",
          "trait_date": "2025-06-18T05:13:45.6760795Z",
          "locale_text": "Drängender Hieb"
        }
      ]
    },
    {
      "locale": "frFR",
      "text": "Bousculade",
      "modification_date": "2025-06-09T13:54:21.7576413Z",
      "translated_from": "enGB",
      "translation_date": "2025-06-09T13:54:21.7576416Z",
      "original_text": "Shoving Strike",
      "traits": [
        {
          "trait": "Translated",
          "trait_date": "2025-06-09T13:54:21.7576426Z",
          "locale_text": "Bousculade"
        }
      ]
    },
    {
      "locale": "zhCN",
      "text": "推搡打击",
      "modification_date": "2025-06-09T10:33:13.2721487Z",
      "translated_from": "enGB",
      "translation_date": "2025-06-09T10:33:13.2721489Z",
      "original_text": "Shoving Strike",
      "traits": [
        {
          "trait": "Translated",
          "trait_date": "2025-06-09T10:33:13.2721500Z",
          "locale_text": "推搡打击"
        }
      ]
    },
    {
      "locale": "esES",
      "text": "Golpe de rechazo",
      "modification_date": "2025-06-10T12:45:03.1479159Z",
      "translated_from": "enGB",
      "translation_date": "2025-06-10T12:45:03.1479162Z",
      "original_text": "Shoving Strike",
      "traits": [
        {
          "trait": "Translated",
          "trait_date": "2025-06-10T12:45:03.1479170Z",
          "locale_text": "Golpe de rechazo"
        }
      ]
    },
    {
      "locale": "jaJP",
      "text": "押し込み攻撃",
      "modification_date": "2025-06-11T08:38:15.3460144Z",
      "translated_from": "enGB",
      "translation_date": "2025-06-16T18:33:55.9606460Z",
      "original_text": "Shoving Strike",
      "traits": [
        {
          "trait": "Translated",
          "trait_date": "2025-06-16T18:33:55.9606473Z",
          "locale_text": "押し込み攻撃"
        }
      ]
    },
    {
      "locale": "trTR",
      "text": "Kakan Atak",
      "modification_date": "2025-06-11T10:33:18.8650943Z",
      "translated_from": "enGB",
      "translation_date": "2025-06-11T10:33:18.8650945Z",
      "original_text": "Shoving Strike",
      "traits": [
        {
          "trait": "Translated",
          "trait_date": "2025-06-11T10:33:18.8650954Z",
          "locale_text": "Kakan Atak"
        }
      ]
    },
    {
      "locale": "Sound",
      "text": "",
      "modification_date": "2025-12-03T12:01:31.2414956Z"
    }
  ],
  "string_traits": [
    {
      "trait": "DLC2",
      "trait_date": "2025-05-26T12:59:20.3934384Z",
      "locale_text": ""
    },
    {
      "trait": "DLC2_mech",
      "trait_date": "2025-05-26T12:59:20.3934395Z",
      "locale_text": ""
    },
    {
      "trait": "механ_выпал",
      "trait_date": "2025-05-26T12:59:20.3934397Z",
      "locale_text": ""
    },
    {
      "trait": "показать_джон_26",
      "trait_date": "2025-05-26T15:14:35.9111578Z",
      "locale_text": ""
    },
    {
      "trait": "механ_28",
      "trait_date": "2025-05-28T08:33:54.4322838Z",
      "locale_text": ""
    },
    {
      "trait": "новый_мех_ушел",
      "trait_date": "2025-06-04T09:06:03.7532521Z",
      "locale_text": ""
    },
    {
      "trait": "Glossary",
      "trait_date": "2026-04-24T07:01:16.5055163Z",
      "locale_text": ""
    }
  ]
}