{
  "source": "ruRU",
  "key": "7eba7df6-316f-4398-aca0-89a80102fe34",
  "ownerGuid": "ce1df2b3234fd774fb541e14bd19d523",
  "languages": [
    {
      "locale": "Sound",
      "text": "",
      "modification_date": "2025-11-26T18:44:29.6138731Z"
    },
    {
      "locale": "ruRU",
      "text": "Массивный перстень вплавлен в камень. На нетронутой плазмой части различим герб Гапраков.",
      "modification_date": "2026-05-25T23:38:31.3690803Z",
      "traits": [
        {
          "trait": "CheckMe",
          "trait_date": "2026-05-25T23:38:31.3690803Z",
          "locale_text": "Массивный перстень вплавлен в камень. На нетронутой плазмой части различим герб Гапраков.",
          "speaker": "",
          "speaker_gender": ""
        }
      ]
    },
    {
      "locale": "enGB",
      "text": "A heavy ring is fused into the stone. On the part that was spared by the plasma, the coat of arms of House Gaprak is barely visible.",
      "modification_date": "2026-05-29T15:16:27.7632284Z",
      "translated_from": "ruRU",
      "translation_date": "2026-05-29T15:16:35.9691676Z",
      "original_text": "Массивный перстень вплавлен в камень. На нетронутой плазмой части различим герб Гапраков.",
      "traits": [
        {
          "trait": "Translated",
          "trait_date": "2026-05-27T14:50:47.0609648Z",
          "locale_text": "A heavy ring is fused into the stone. On the part that was spared by the plasma, you can barely identify the coat of arms of House Gaprak."
        },
        {
          "trait": "Edited",
          "trait_date": "2026-05-29T15:16:27.7632302Z",
          "locale_text": "A heavy ring is fused into the stone. On the part that was spared by the plasma, the coat of arms of House Gaprak is barely visible."
        },
        {
          "trait": "AD_tr_ed",
          "trait_date": "2026-04-22T08:00:11.1196625Z",
          "locale_text": "A heavy ring lies in the dirt. It bears the coat of arms of House Gaprak."
        },
        {
          "trait": "TK_tr",
          "trait_date": "2026-05-27T14:49:53.7280667Z",
          "locale_text": "A heavy ring is fused into the stone. On the part that was spared by the plasma, you can barely identify the coat of arms of House Gaprak."
        },
        {
          "trait": "FG_ed",
          "trait_date": "2026-05-29T15:16:27.7632310Z",
          "locale_text": "A heavy ring is fused into the stone. On the part that was spared by the plasma, the coat of arms of House Gaprak is barely visible."
        },
        {
          "trait": "TK_rv",
          "trait_date": "2026-05-29T15:16:35.9691850Z",
          "locale_text": "A heavy ring is fused into the stone. On the part that was spared by the plasma, the coat of arms of House Gaprak is barely visible."
        }
      ]
    },
    {
      "locale": "deDE",
      "text": "Ein schwerer Ring mit dem Stein verschmolzen. Auf dem vom Plasma verschonte Teil ist mit Mühe das Wappen von Haus Gaprak zu erkennen.",
      "modification_date": "2026-06-09T13:30:51.3453059Z",
      "translated_from": "enGB",
      "translation_date": "2026-06-09T13:30:51.3453060Z",
      "original_text": "A heavy ring is fused into the stone. On the part that was spared by the plasma, the coat of arms of House Gaprak is barely visible.",
      "traits": [
        {
          "trait": "Translated",
          "trait_date": "2026-06-09T13:30:51.3453067Z",
          "locale_text": "Ein schwerer Ring mit dem Stein verschmolzen. Auf dem vom Plasma verschonte Teil ist mit Mühe das Wappen von Haus Gaprak zu erkennen."
        }
      ]
    },
    {
      "locale": "zhCN",
      "text": "一个沉重的圆环熔铸在石头里。通过未被等离子灼烧的那部分，依稀能看出这是贾帕克家族的纹章。",
      "modification_date": "2026-06-09T13:59:31.1524473Z",
      "translated_from": "enGB",
      "translation_date": "2026-06-09T13:59:31.1524475Z",
      "original_text": "A heavy ring is fused into the stone. On the part that was spared by the plasma, the coat of arms of House Gaprak is barely visible.",
      "traits": [
        {
          "trait": "Translated",
          "trait_date": "2026-06-09T13:59:31.1524485Z",
          "locale_text": "一个沉重的圆环熔铸在石头里。通过未被等离子灼烧的那部分，依稀能看出这是贾帕克家族的纹章。"
        }
      ]
    },
    {
      "locale": "frFR",
      "text": "Une chevalière a fusionné avec la pierre. Sur la partie épargnée par le plasma, on distingue vaguement les armoiries de la maison Gaprak.",
      "modification_date": "2026-06-10T07:19:02.3691911Z",
      "translated_from": "enGB",
      "translation_date": "2026-06-10T07:19:02.3691912Z",
      "original_text": "A heavy ring is fused into the stone. On the part that was spared by the plasma, the coat of arms of House Gaprak is barely visible.",
      "traits": [
        {
          "trait": "Translated",
          "trait_date": "2026-06-10T07:19:02.3691920Z",
          "locale_text": "Une chevalière a fusionné avec la pierre. Sur la partie épargnée par le plasma, on distingue vaguement les armoiries de la maison Gaprak."
        }
      ]
    },
    {
      "locale": "esES",
      "text": "Un anillo pesado está fundido con la piedra. En la parte que no ha alcanzado el plasma, se identifica a duras penas el escudo de armas de la casa Gaprak.",
      "modification_date": "2026-06-08T15:16:26.7429859Z",
      "translated_from": "enGB",
      "translation_date": "2026-06-08T15:16:26.7429860Z",
      "original_text": "A heavy ring is fused into the stone. On the part that was spared by the plasma, the coat of arms of House Gaprak is barely visible.",
      "traits": [
        {
          "trait": "Translated",
          "trait_date": "2026-06-08T15:16:26.7429865Z",
          "locale_text": "Un anillo pesado está fundido con la piedra. En la parte que no ha alcanzado el plasma, se identifica a duras penas el escudo de armas de la casa Gaprak."
        }
      ]
    },
    {
      "locale": "trTR",
      "text": "Ağır bir yüzük, taşa kaynaşmış. Plazmanın zarar vermediği kısmında Gaprak Hanesi'nin arması zar zor seçiliyor.",
      "modification_date": "2026-06-10T07:24:43.8471997Z",
      "translated_from": "enGB",
      "translation_date": "2026-06-10T07:24:43.8471999Z",
      "original_text": "A heavy ring is fused into the stone. On the part that was spared by the plasma, the coat of arms of House Gaprak is barely visible.",
      "traits": [
        {
          "trait": "Translated",
          "trait_date": "2026-06-10T07:24:43.8472009Z",
          "locale_text": "Ağır bir yüzük, taşa kaynaşmış. Plazmanın zarar vermediği kısmında Gaprak Hanesi'nin arması zar zor seçiliyor."
        }
      ]
    },
    {
      "locale": "jaJP",
      "text": "重厚なリングが石に熔け込んでいる。プラズマの攻撃を免れた部分には、ガプラク家の紋章がかすかに残っている。",
      "modification_date": "2026-06-05T13:05:47.6866916Z",
      "translated_from": "enGB",
      "translation_date": "2026-06-05T14:15:02.5924564Z",
      "original_text": "A heavy ring is fused into the stone. On the part that was spared by the plasma, the coat of arms of House Gaprak is barely visible.",
      "traits": [
        {
          "trait": "AIGenerated",
          "trait_date": "2026-06-05T14:15:02.5924577Z",
          "locale_text": "重厚なリングが石に熔け込んでいる。プラズマの攻撃を免れた部分には、ガプラク家の紋章がかすかに残っている。"
        }
      ]
    }
  ],
  "string_traits": [
    {
      "trait": "DLC3",
      "trait_date": "2026-05-27T15:10:39.1932321Z",
      "locale_text": ""
    },
    {
      "trait": "DLC3_lore",
      "trait_date": "2026-05-27T15:10:39.1932323Z",
      "locale_text": ""
    },
    {
      "trait": "остаткилупа_эшли",
      "trait_date": "2026-04-15T09:47:16.4879009Z",
      "locale_text": ""
    },
    {
      "trait": "в_работе",
      "trait_date": "2026-05-27T15:10:39.1932326Z",
      "locale_text": ""
    },
    {
      "trait": "шестнадцатый_языки",
      "trait_date": "2026-04-22T08:05:03.3826111Z",
      "locale_text": ""
    },
    {
      "trait": "Sent_otherloc",
      "trait_date": "2026-05-06T11:18:22.5696172Z",
      "locale_text": ""
    },
    {
      "trait": "второй_тарасу",
      "trait_date": "2026-05-26T09:09:30.9320341Z",
      "locale_text": ""
    },
    {
      "trait": "кэжуаласап",
      "trait_date": "2026-05-26T14:21:28.3169870Z",
      "locale_text": ""
    },
    {
      "trait": "почтифинальный_редактура",
      "trait_date": "2026-05-27T15:07:14.5477601Z",
      "locale_text": ""
    },
    {
      "trait": "Sent_editing",
      "trait_date": "2026-05-27T15:10:39.1932316Z",
      "locale_text": ""
    },
    {
      "trait": "Major",
      "trait_date": "2026-05-28T10:44:47.1946472Z",
      "locale_text": ""
    },
    {
      "trait": "точно_обновить_локали",
      "trait_date": "2026-05-28T10:44:47.1946476Z",
      "locale_text": ""
    },
    {
      "trait": "поедет_языки_206",
      "trait_date": "2026-06-01T14:48:36.2707069Z",
      "locale_text": ""
    }
  ]
}