{
  "source": "enGB",
  "key": "8fb08688-fc65-4d4d-9494-2efabffc1d49",
  "ownerGuid": "69e61aa783afbe54aa58c2b8c9236020",
  "languages": [
    {
      "locale": "enGB",
      "text": "General",
      "modification_date": "2017-07-04T17:05:43.2934850Z",
      "translated_from": "ruRU",
      "translation_date": "2023-08-02T11:22:30.4042478Z",
      "original_text": "Общие",
      "traits": [
        {
          "trait": "Translated",
          "trait_date": "2018-02-17T14:03:39.0004160Z",
          "locale_text": "General"
        },
        {
          "trait": "Relevant",
          "trait_date": "2018-03-22T17:41:39.3781730Z",
          "locale_text": "General"
        },
        {
          "trait": "Final",
          "trait_date": "2018-03-22T17:41:39.3781730Z",
          "locale_text": "General"
        },
        {
          "trait": "Turkish",
          "trait_date": "2024-11-20T11:18:47.2864004Z",
          "locale_text": "General"
        }
      ]
    },
    {
      "locale": "ruRU",
      "text": "Общие",
      "modification_date": "2018-06-14T13:36:28.5435216Z",
      "traits": []
    },
    {
      "locale": "deDE",
      "text": "Allgemein",
      "modification_date": "2018-06-29T16:01:38.2072554Z",
      "translated_from": "enGB",
      "translation_date": "2024-11-26T09:42:17.8211706Z",
      "original_text": "General",
      "traits": [
        {
          "trait": "Translated",
          "trait_date": "2018-07-23T14:55:43.6102552Z",
          "locale_text": "Allgemein"
        }
      ]
    },
    {
      "locale": "frFR",
      "text": "Général",
      "modification_date": "2018-06-30T22:12:41.3154675Z",
      "translated_from": "enGB",
      "translation_date": "2024-11-26T07:19:18.0344108Z",
      "original_text": "General",
      "traits": [
        {
          "trait": "Translated",
          "trait_date": "2018-06-30T22:12:41.3154675Z",
          "locale_text": "Général"
        }
      ]
    },
    {
      "locale": "zhCN",
      "text": "通用",
      "modification_date": "2018-07-02T20:46:55.3019649Z",
      "translated_from": "enGB",
      "translation_date": "2019-05-31T14:28:13.4900835Z",
      "original_text": "General",
      "traits": [
        {
          "trait": "Translated",
          "trait_date": "2019-05-31T14:28:13.4900835Z",
          "locale_text": "通用"
        },
        {
          "trait": "Relevant",
          "trait_date": "2020-11-15T15:36:52.9376919Z",
          "locale_text": "通用"
        }
      ]
    },
    {
      "locale": "esES",
      "text": "General",
      "modification_date": "2023-09-05T18:26:32.5497986Z",
      "translated_from": "enGB",
      "translation_date": "2023-09-25T18:54:59.8656972Z",
      "original_text": "General",
      "traits": [
        {
          "trait": "Translated",
          "trait_date": "2023-09-25T18:54:59.8656982Z",
          "locale_text": "General"
        }
      ]
    },
    {
      "locale": "jaJP",
      "text": "一般",
      "modification_date": "2023-09-05T18:26:50.2353353Z",
      "translated_from": "enGB",
      "translation_date": "2025-01-17T10:25:59.2980090Z",
      "original_text": "General",
      "traits": [
        {
          "trait": "Translated",
          "trait_date": "2025-01-17T10:25:59.2980105Z",
          "locale_text": "一般"
        }
      ]
    },
    {
      "locale": "trTR",
      "text": "Genel",
      "modification_date": "2024-12-02T15:10:19.8368471Z",
      "translated_from": "enGB",
      "translation_date": "2024-12-02T15:10:19.8368473Z",
      "original_text": "General",
      "traits": [
        {
          "trait": "Translated",
          "trait_date": "2026-06-10T16:44:30.0145606Z",
          "locale_text": "Genel"
        }
      ]
    },
    {
      "locale": "Sound",
      "text": "",
      "modification_date": "2025-12-03T13:33:04.8186958Z"
    }
  ],
  "string_traits": [
    {
      "trait": "левшеяп",
      "trait_date": "2025-01-17T10:33:02.9666540Z",
      "locale_text": ""
    }
  ]
}