{
  "source": "enGB",
  "key": "6673115b-5b66-4eca-b3e2-69a3c838dc08",
  "ownerGuid": "491376ba918978a4ea09fe7a156a6e31",
  "languages": [
    {
      "locale": "enGB",
      "text": "In this section, you will be able to choose abilities from the second-tier archetype. At the moment, a second-tier archetype has not been selected. Level characters up to develop a more diverse roster of abilities.",
      "modification_date": "2023-12-29T11:13:57.4662272Z",
      "translated_from": "ruRU",
      "translation_date": "2023-10-04T16:06:00.8976999Z",
      "original_text": "Здесь вы сможете выбрать способности архетипа второй ступени. Сейчас архетип второй ступени не выбран. Повышайте уровень персонажей, чтобы разнообразить набор способностей.",
      "traits": [
        {
          "trait": "Edited",
          "trait_date": "2023-08-25T08:12:40.9241681Z",
          "locale_text": "In this section, you will be able to choose abilities from the second-tier doctrine. At the moment, the second-tier doctrine has not been selected. Level characters up to develop a more diverse roster of abilities."
        },
        {
          "trait": "JL_ed",
          "trait_date": "2024-07-29T06:57:14.4902234Z",
          "locale_text": "In this section, you will be able to choose abilities from the second-tier archetype. At the moment, a second-tier archetype has not been selected. Level characters up to develop a more diverse roster of abilities."
        },
        {
          "trait": "Turkish",
          "trait_date": "2024-11-08T06:45:52.0167869Z",
          "locale_text": "In this section, you will be able to choose abilities from the second-tier archetype. At the moment, a second-tier archetype has not been selected. Level characters up to develop a more diverse roster of abilities."
        }
      ]
    },
    {
      "locale": "esES",
      "text": "En esta sección, podrás elegir capacidades del arquetipo de segunda categoría. En este momento no has elegido un arquetipo de segunda categoría. Sube de nivel a tus personajes para obtener una gama más variada de capacidades.",
      "modification_date": "2023-11-21T18:34:54.4349015Z",
      "translated_from": "enGB",
      "translation_date": "2023-11-21T18:34:54.4349017Z",
      "original_text": "In this section, you will be able to choose abilities from the second-tier archetype. At the moment, a second-tier archetype has not been selected. Level characters up to develop a more diverse roster of abilities.",
      "traits": [
        {
          "trait": "Translated",
          "trait_date": "2023-09-04T18:28:26.4895523Z",
          "locale_text": "En esta sección, podrás elegir capacidades de la doctrina de segunda categoría. En este momento no has elegido una doctrina de segunda categoría. Sube de nivel a tus personajes para obtener una gama más variada de capacidades."
        }
      ]
    },
    {
      "locale": "jaJP",
      "text": "このセクションでは、ティア2のタイプ・アビリティを選べます。現在、ティア2のタイプは未選択の状態です。キャラクターのレベルを上げて、様々な種類のアビリティを解放しましょう。",
      "modification_date": "2025-01-17T10:26:03.8017123Z",
      "translated_from": "enGB",
      "translation_date": "2025-01-17T10:26:03.8017124Z",
      "original_text": "In this section, you will be able to choose abilities from the second-tier archetype. At the moment, a second-tier archetype has not been selected. Level characters up to develop a more diverse roster of abilities.",
      "traits": [
        {
          "trait": "Translated",
          "trait_date": "2025-01-17T10:26:03.8017128Z",
          "locale_text": "このセクションでは、ティア2のタイプ・アビリティを選べます。現在、ティア2のタイプは未選択の状態です。キャラクターのレベルを上げて、様々な種類のアビリティを解放しましょう。"
        }
      ]
    },
    {
      "locale": "zhCN",
      "text": "您可以在此选择二级职业的相关能力。您目前并未选择该二级职业。提升角色等级可以解锁各种各样的新能力。",
      "modification_date": "2023-11-17T11:20:41.7049356Z",
      "translated_from": "enGB",
      "translation_date": "2023-11-17T11:20:41.7049359Z",
      "original_text": "In this section, you will be able to choose abilities from the second-tier archetype. At the moment, a second-tier archetype has not been selected. Level characters up to develop a more diverse roster of abilities.",
      "traits": [
        {
          "trait": "Translated",
          "trait_date": "2023-09-04T18:28:27.8561672Z",
          "locale_text": "您可以在此选择二级信条的相关能力。您目前并未选择该二级信条。提升角色等级可以解锁各种各样的新能力。"
        }
      ]
    },
    {
      "locale": "ruRU",
      "text": "Здесь вы сможете выбрать способности архетипа второй ступени. Сейчас архетип второй ступени не выбран. Повышайте уровень персонажей, чтобы разнообразить набор способностей.",
      "modification_date": "2023-11-27T11:18:59.9857306Z",
      "translated_from": "enGB",
      "translation_date": "2023-09-04T19:23:08.3069156Z",
      "original_text": "In this section, you will be able to choose abilities from the second-tier archetype. At the moment, a second-tier archetype has not been selected. Level characters up to develop a more diverse roster of abilities.",
      "traits": [
        {
          "trait": "Translated",
          "trait_date": "2023-09-04T19:23:08.3069169Z",
          "locale_text": "Здесь вы сможете выбрать способности доктрины второй ступени. Сейчас доктрина второй ступени не выбрана. Повышайте уровень персонажей, чтобы разнообразить набор способностей."
        },
        {
          "trait": "ASA_tr",
          "trait_date": "2023-09-04T19:23:08.3069173Z",
          "locale_text": "Здесь вы сможете выбрать способности доктрины второй ступени. Сейчас доктрина второй ступени не выбрана. Повышайте уровень персонажей, чтобы разнообразить набор способностей."
        }
      ]
    },
    {
      "locale": "deDE",
      "text": "In diesem Abschnitt kannst du Fähigkeiten aus dem zweitrangigem Archetyp auswählen. Im Moment ist noch kein zweitrangiger Archetyp ausgewählt. Steigere die Stufe deiner Charaktere, um eine größere Vielfalt an Fähigkeiten zu entwickeln.",
      "modification_date": "2023-12-29T10:58:55.1462142Z",
      "translated_from": "enGB",
      "translation_date": "2024-11-26T09:42:25.3119551Z",
      "original_text": "In this section, you will be able to choose abilities from the second-tier archetype. At the moment, a second-tier archetype has not been selected. Level characters up to develop a more diverse roster of abilities.",
      "traits": [
        {
          "trait": "Translated",
          "trait_date": "2023-09-11T11:50:23.7454061Z",
          "locale_text": "In diesem Abschnitt kannst du Fähigkeiten aus der zweitrangigen Doktrin auswählen. Im Moment ist noch keine zweitrangige Doktrin ausgewählt. Steigere die Stufe deiner Charaktere, um eine größere Vielfalt an Fähigkeiten zu entwickeln."
        }
      ]
    },
    {
      "locale": "frFR",
      "text": "Cette section vous permet de choisir des capacités à partir de l'archétype de deuxième niveau. Pour le moment, aucun archétype de deuxième niveau n'est sélectionné. Augmentez le niveau de vos personnages afin d'accéder à un plus large éventail de capacités.",
      "modification_date": "2024-11-26T07:19:30.2426072Z",
      "translated_from": "enGB",
      "translation_date": "2024-11-26T07:19:30.2426075Z",
      "original_text": "In this section, you will be able to choose abilities from the second-tier archetype. At the moment, a second-tier archetype has not been selected. Level characters up to develop a more diverse roster of abilities.",
      "traits": [
        {
          "trait": "Translated",
          "trait_date": "2023-09-11T11:50:25.4829704Z",
          "locale_text": "Cette section vous permet de choisir des capacités à partir de la doctrine de deuxième niveau. Pour le moment, la doctrine de deuxième niveau n'est pas sélectionnée. Augmentez le niveau de vos personnages afin d'accéder à un plus large éventail de capacités."
        }
      ]
    },
    {
      "locale": "trTR",
      "text": "Bu kısımdan ikinci derece arketip kabiliyetleri seçebileceksin. Şu anda ikinci derece bir arketip seçilmedi. Daha çok çeşit sunan bir kabiliyet listesi için karakterlerine seviye atlat.",
      "modification_date": "2024-12-02T15:09:49.5196698Z",
      "translated_from": "enGB",
      "translation_date": "2024-12-02T15:09:49.5196700Z",
      "original_text": "In this section, you will be able to choose abilities from the second-tier archetype. At the moment, a second-tier archetype has not been selected. Level characters up to develop a more diverse roster of abilities.",
      "traits": [
        {
          "trait": "Translated",
          "trait_date": "2026-06-10T16:44:36.6067183Z",
          "locale_text": "Bu kısımdan ikinci derece arketip kabiliyetleri seçebileceksin. Şu anda ikinci derece bir arketip seçilmedi. Daha çok çeşit sunan bir kabiliyet listesi için karakterlerine seviye atlat."
        }
      ]
    },
    {
      "locale": "Sound",
      "text": "",
      "modification_date": "2025-12-03T09:31:38.8605732Z"
    }
  ],
  "string_traits": [
    {
      "trait": "левшеяп",
      "trait_date": "2025-01-17T10:33:09.6365136Z",
      "locale_text": ""
    }
  ]
}