{
  "source": "dev",
  "key": "80a75f0d-d95f-4873-96db-49d2a2d33b8a",
  "ownerGuid": "5452d1c713c2be542a409d40bbe1cc4b",
  "languages": [
    {
      "locale": "Sound",
      "text": "",
      "modification_date": "2026-02-17T08:15:19.9292388Z"
    },
    {
      "locale": "dev",
      "text": "Canoptek Grounding Protocols",
      "modification_date": "2026-02-17T08:15:21.6674261Z",
      "traits": [
        {
          "trait": "CheckMe",
          "trait_date": "2026-02-17T08:15:21.6706565Z",
          "locale_text": "Canoptek Grounding Protocols",
          "speaker": "",
          "speaker_gender": ""
        }
      ]
    },
    {
      "locale": "enGB",
      "text": "Flying",
      "modification_date": "2026-04-09T13:16:35.3837255Z",
      "translated_from": "dev",
      "translation_date": "2026-04-09T13:16:37.6929439Z",
      "original_text": "Canoptek Grounding Protocols",
      "traits": [
        {
          "trait": "GD_ok",
          "trait_date": "2026-04-09T13:16:42.8265673Z",
          "locale_text": "Flying"
        },
        {
          "trait": "Edited",
          "trait_date": "2026-04-09T14:24:05.4069748Z",
          "locale_text": "Flying"
        },
        {
          "trait": "JL_ed",
          "trait_date": "2026-04-09T14:24:05.4069751Z",
          "locale_text": "Flying"
        }
      ]
    },
    {
      "locale": "ruRU",
      "text": "Полет",
      "modification_date": "2026-04-09T13:17:04.2387323Z",
      "translated_from": "enGB",
      "translation_date": "2026-04-09T13:17:06.0587888Z",
      "original_text": "Flying",
      "traits": [
        {
          "trait": "Translated",
          "trait_date": "2026-04-09T13:17:10.9856957Z",
          "locale_text": "Полет"
        }
      ]
    },
    {
      "locale": "frFR",
      "text": "Vol",
      "modification_date": "2026-04-17T10:13:52.0962044Z",
      "translated_from": "enGB",
      "translation_date": "2026-04-17T10:13:52.0962045Z",
      "original_text": "Flying",
      "traits": [
        {
          "trait": "Translated",
          "trait_date": "2026-04-17T10:13:52.0962054Z",
          "locale_text": "Vol"
        }
      ]
    },
    {
      "locale": "trTR",
      "text": "Uçuş",
      "modification_date": "2026-04-20T07:31:19.2400539Z",
      "translated_from": "enGB",
      "translation_date": "2026-04-20T07:31:19.2400541Z",
      "original_text": "Flying",
      "traits": [
        {
          "trait": "Translated",
          "trait_date": "2026-04-20T07:31:19.2400552Z",
          "locale_text": "Uçuş"
        }
      ]
    },
    {
      "locale": "zhCN",
      "text": "飞行",
      "modification_date": "2026-04-20T07:33:45.2640774Z",
      "translated_from": "enGB",
      "translation_date": "2026-04-20T07:33:45.2640776Z",
      "original_text": "Flying",
      "traits": [
        {
          "trait": "Translated",
          "trait_date": "2026-04-20T07:33:45.2640781Z",
          "locale_text": "飞行"
        }
      ]
    },
    {
      "locale": "esES",
      "text": "Volador",
      "modification_date": "2026-04-20T07:48:11.7137001Z",
      "translated_from": "enGB",
      "translation_date": "2026-04-20T07:48:11.7137003Z",
      "original_text": "Flying",
      "traits": [
        {
          "trait": "Translated",
          "trait_date": "2026-04-20T07:48:11.7137011Z",
          "locale_text": "Volador"
        }
      ]
    },
    {
      "locale": "deDE",
      "text": "Fliegt",
      "modification_date": "2026-04-24T10:25:08.7129262Z",
      "translated_from": "enGB",
      "translation_date": "2026-04-24T10:25:08.7129264Z",
      "original_text": "Flying",
      "traits": [
        {
          "trait": "Translated",
          "trait_date": "2026-04-24T10:25:08.7129269Z",
          "locale_text": "Fliegt"
        }
      ]
    },
    {
      "locale": "jaJP",
      "text": "飛行機で飛ぶ",
      "modification_date": "2026-06-05T13:06:47.0572360Z",
      "translated_from": "enGB",
      "translation_date": "2026-06-05T14:15:06.6420269Z",
      "original_text": "Flying",
      "traits": [
        {
          "trait": "AIGenerated",
          "trait_date": "2026-06-05T14:15:06.6420275Z",
          "locale_text": "飛行機で飛ぶ"
        }
      ]
    }
  ],
  "string_traits": [
    {
      "trait": "второй_батч_механ",
      "trait_date": "2026-04-10T11:34:36.3235188Z",
      "locale_text": ""
    },
    {
      "trait": "Sent_otherloc",
      "trait_date": "2026-04-13T09:05:53.7424648Z",
      "locale_text": ""
    },
    {
      "trait": "в_работе",
      "trait_date": "2026-04-13T09:05:53.7424650Z",
      "locale_text": ""
    },
    {
      "trait": "DLC3",
      "trait_date": "2026-04-16T14:28:38.0952209Z",
      "locale_text": ""
    },
    {
      "trait": "DLC3_mech",
      "trait_date": "2026-04-16T14:28:38.0952217Z",
      "locale_text": ""
    },
    {
      "trait": "Glossary",
      "trait_date": "2026-04-24T06:58:21.3467925Z",
      "locale_text": ""
    }
  ]
}