{
  "source": "ruRU",
  "key": "eea2207d-c06a-472b-aea8-3cc5d984a21e",
  "ownerGuid": "3cbc40cc63aafa54e80dce14502522a2",
  "languages": [
    {
      "locale": "ruRU",
      "text": "Клеменциа Версериан",
      "modification_date": "2022-03-24T10:34:26.3548780Z",
      "traits": [
        {
          "trait": "CheckMe",
          "trait_date": "2021-12-22T08:40:34.6760036Z",
          "locale_text": "[Draft] Clemence"
        },
        {
          "trait": "Translated",
          "trait_date": "2026-06-04T08:29:15.7904645Z",
          "locale_text": "Клеменциа Версериан"
        }
      ]
    },
    {
      "locale": "enGB",
      "text": "Clementia Werserian",
      "modification_date": "2022-04-15T10:22:25.7823652Z",
      "translated_from": "ruRU",
      "translation_date": "2023-08-16T16:46:11.1811760Z",
      "original_text": "Клеменциа Версериан",
      "traits": [
        {
          "trait": "Edited",
          "trait_date": "2023-09-13T14:24:17.2883232Z",
          "locale_text": "Clementia Werserian"
        },
        {
          "trait": "JL_ed",
          "trait_date": "2023-09-13T14:24:17.2883239Z",
          "locale_text": "Clementia Werserian"
        },
        {
          "trait": "Turkish",
          "trait_date": "2024-10-23T10:30:38.3957003Z",
          "locale_text": "Clementia Werserian"
        }
      ]
    },
    {
      "locale": "deDE",
      "text": "Clementia Werserian",
      "modification_date": "2023-09-04T20:23:05.3899412Z",
      "translated_from": "enGB",
      "translation_date": "2024-11-26T09:42:17.1613939Z",
      "original_text": "Clementia Werserian",
      "traits": [
        {
          "trait": "Translated",
          "trait_date": "2023-10-18T19:12:34.7415300Z",
          "locale_text": "Clementia Werserian"
        }
      ]
    },
    {
      "locale": "frFR",
      "text": "Clémentia Werserian",
      "modification_date": "2023-09-25T18:57:24.8863540Z",
      "translated_from": "enGB",
      "translation_date": "2024-11-26T07:19:17.1412871Z",
      "original_text": "Clementia Werserian",
      "traits": [
        {
          "trait": "Translated",
          "trait_date": "2023-10-18T19:21:19.9476616Z",
          "locale_text": "Clémentia Werserian"
        }
      ]
    },
    {
      "locale": "zhCN",
      "text": "克莱门缇雅·韦尔森",
      "modification_date": "2023-09-20T11:39:37.2790087Z",
      "translated_from": "enGB",
      "translation_date": "2023-09-20T11:39:37.2790089Z",
      "original_text": "Clementia Werserian",
      "traits": [
        {
          "trait": "Translated",
          "trait_date": "2023-09-20T11:39:37.2790099Z",
          "locale_text": "克莱门缇雅·韦尔森"
        }
      ]
    },
    {
      "locale": "esES",
      "text": "Clementia Werserian",
      "modification_date": "2023-09-05T18:26:36.0647827Z",
      "translated_from": "enGB",
      "translation_date": "2023-09-20T10:49:13.1009967Z",
      "original_text": "Clementia Werserian",
      "traits": [
        {
          "trait": "Translated",
          "trait_date": "2023-09-20T10:49:13.1010002Z",
          "locale_text": "Clementia Werserian"
        }
      ]
    },
    {
      "locale": "jaJP",
      "text": "クレメンティア・ウェルザリアン",
      "modification_date": "2023-09-29T08:19:58.3045593Z",
      "translated_from": "enGB",
      "translation_date": "2023-10-20T07:52:24.1841998Z",
      "original_text": "Clementia Werserian",
      "traits": [
        {
          "trait": "Translated",
          "trait_date": "2023-10-20T07:52:24.1842013Z",
          "locale_text": "クレメンティア・ウェルザリアン"
        }
      ]
    },
    {
      "locale": "trTR",
      "text": "Clementia Werserian",
      "modification_date": "2024-12-02T15:08:58.0040261Z",
      "translated_from": "enGB",
      "translation_date": "2024-12-02T15:08:58.0040263Z",
      "original_text": "Clementia Werserian",
      "traits": [
        {
          "trait": "Translated",
          "trait_date": "2026-06-10T16:45:05.4650038Z",
          "locale_text": "Clementia Werserian"
        }
      ]
    },
    {
      "locale": "Sound",
      "text": "",
      "modification_date": "2025-12-03T11:34:36.2961817Z"
    }
  ],
  "string_traits": [
    {
      "trait": "Glossary",
      "trait_date": "2026-04-24T06:58:28.7420805Z",
      "locale_text": ""
    }
  ]
}