{
  "source": "ruRU",
  "key": "6c490607-92ea-4766-a937-d628019c3efd",
  "ownerGuid": "d934ca1614544897be5cb622943e33ff",
  "languages": [
    {
      "locale": "ruRU",
      "text": "[Активировать протокол \"Затмение\"]",
      "modification_date": "2024-04-12T18:30:02.8893231Z",
      "traits": []
    },
    {
      "locale": "dev",
      "text": "",
      "modification_date": "2024-04-12T18:29:53.2821688Z",
      "traits": []
    },
    {
      "locale": "enGB",
      "text": "[Activate the Eclipse protocol]",
      "modification_date": "2024-05-16T21:13:10.7975049Z",
      "translated_from": "ruRU",
      "translation_date": "2024-05-16T21:13:10.7975056Z",
      "original_text": "[Активировать протокол \"Затмение\"]",
      "traits": [
        {
          "trait": "Translated",
          "trait_date": "2024-05-02T05:12:45.7704078Z",
          "locale_text": "[Activate the \"Eclipse\" protocol]"
        },
        {
          "trait": "MS_tr",
          "trait_date": "2024-05-02T05:12:45.7704084Z",
          "locale_text": "[Activate the \"Eclipse\" protocol]"
        },
        {
          "trait": "Edited",
          "trait_date": "2024-05-08T15:51:41.7126850Z",
          "locale_text": "[Activate the \"Eclipse\" protocol]"
        },
        {
          "trait": "FG_ed",
          "trait_date": "2024-05-08T15:51:41.7126853Z",
          "locale_text": "[Activate the \"Eclipse\" protocol]"
        },
        {
          "trait": "TK_rv",
          "trait_date": "2024-05-16T21:13:10.7975077Z",
          "locale_text": "[Activate the Eclipse protocol]"
        },
        {
          "trait": "Turkish",
          "trait_date": "2024-08-29T09:17:07.0174236Z",
          "locale_text": "[Activate the Eclipse protocol]"
        }
      ]
    },
    {
      "locale": "esES",
      "text": "[Activar el protocolo Eclipse]",
      "modification_date": "2024-06-24T19:23:54.7243750Z",
      "translated_from": "enGB",
      "translation_date": "2024-06-24T19:23:54.7243752Z",
      "original_text": "[Activate the Eclipse protocol]",
      "traits": [
        {
          "trait": "Translated",
          "trait_date": "2024-06-24T19:23:54.7243771Z",
          "locale_text": "[Activar el protocolo Eclipse]"
        }
      ]
    },
    {
      "locale": "jaJP",
      "text": "[衰退プロトコルを起動する]",
      "modification_date": "2024-06-24T19:25:17.3046139Z",
      "translated_from": "enGB",
      "translation_date": "2024-06-24T19:25:17.3046143Z",
      "original_text": "[Activate the Eclipse protocol]",
      "traits": [
        {
          "trait": "Translated",
          "trait_date": "2024-06-24T19:25:17.3046162Z",
          "locale_text": "[衰退プロトコルを起動する]"
        }
      ]
    },
    {
      "locale": "zhCN",
      "text": "[激活日蚀协议]",
      "modification_date": "2024-06-24T19:26:49.6014009Z",
      "translated_from": "enGB",
      "translation_date": "2024-06-24T19:26:49.6014012Z",
      "original_text": "[Activate the Eclipse protocol]",
      "traits": [
        {
          "trait": "Translated",
          "trait_date": "2024-06-24T19:26:49.6014033Z",
          "locale_text": "[激活日蚀协议]"
        }
      ]
    },
    {
      "locale": "deDE",
      "text": "[Das Eclipse-Protokoll aktivieren]",
      "modification_date": "2024-07-15T11:50:53.4654378Z",
      "translated_from": "enGB",
      "translation_date": "2024-07-15T11:50:53.4654381Z",
      "original_text": "[Activate the Eclipse protocol]",
      "traits": [
        {
          "trait": "Translated",
          "trait_date": "2024-07-15T11:50:53.4654407Z",
          "locale_text": "[Das Eclipse-Protokoll aktivieren]"
        }
      ]
    },
    {
      "locale": "frFR",
      "text": "[Activer le protocole Éclipse]",
      "modification_date": "2024-07-26T18:28:28.3102776Z",
      "translated_from": "enGB",
      "translation_date": "2024-07-26T18:28:28.3102779Z",
      "original_text": "[Activate the Eclipse protocol]",
      "traits": [
        {
          "trait": "Translated",
          "trait_date": "2024-07-26T18:28:28.3102795Z",
          "locale_text": "[Activer le protocole Éclipse]"
        }
      ]
    },
    {
      "locale": "trTR",
      "text": "[Tutulma protokolünü etkinleştir]",
      "modification_date": "2025-01-21T10:49:07.5983369Z",
      "translated_from": "enGB",
      "translation_date": "2025-01-21T10:49:07.5983371Z",
      "original_text": "[Activate the Eclipse protocol]",
      "traits": [
        {
          "trait": "Translated",
          "trait_date": "2026-06-10T16:43:26.7701407Z",
          "locale_text": "[Tutulma protokolünü etkinleştir]"
        }
      ]
    },
    {
      "locale": "Sound",
      "text": "",
      "modification_date": "2025-12-03T10:21:20.1961400Z"
    }
  ],
  "string_traits": [
    {
      "trait": "DLC1",
      "trait_date": "2024-04-23T15:27:22.1742589Z",
      "locale_text": ""
    }
  ]
}